LinuxCApiRef/README.md
LinuxCApiRef/__init__.py
LinuxCApiRef/__main__.py
LinuxCApiRef/file.epub
LinuxCApiRef/index.html
LinuxCApiRef/css/__init__.py
LinuxCApiRef/css/annotations.css
LinuxCApiRef/css/main.css
LinuxCApiRef/css/normalize.css
LinuxCApiRef/css/popup.css
LinuxCApiRef/font/__init__.py
LinuxCApiRef/font/fontello.eot
LinuxCApiRef/font/fontello.svg
LinuxCApiRef/font/fontello.ttf
LinuxCApiRef/font/fontello.woff
LinuxCApiRef/img/__init__.py
LinuxCApiRef/img/annotator-glyph-sprite.png
LinuxCApiRef/img/annotator-icon-sprite.png
LinuxCApiRef/img/apple-touch-icon.png
LinuxCApiRef/img/cancelfullscreen.png
LinuxCApiRef/img/close.png
LinuxCApiRef/img/fullscreen.png
LinuxCApiRef/img/loader.gif
LinuxCApiRef/img/menu-icon.png
LinuxCApiRef/img/save.png
LinuxCApiRef/img/saved.png
LinuxCApiRef/img/settings-s.png
LinuxCApiRef/img/settings.png
LinuxCApiRef/img/star.png
LinuxCApiRef/js/__init__.py
LinuxCApiRef/js/epub.js
LinuxCApiRef/js/epub.min.js
LinuxCApiRef/js/epub.min.map
LinuxCApiRef/js/hooks.min.js
LinuxCApiRef/js/hooks.min.map
LinuxCApiRef/js/reader.js
LinuxCApiRef/js/reader.js.map
LinuxCApiRef/js/reader.min.js
LinuxCApiRef/js/reader.min.map
LinuxCApiRef/js/hooks/__init__.py
LinuxCApiRef/js/hooks/extensions/__init__.py
LinuxCApiRef/js/hooks/extensions/highlight.js
LinuxCApiRef/js/libs/__init__.py
LinuxCApiRef/js/libs/jquery.min.js
LinuxCApiRef/js/libs/localforage.min.js
LinuxCApiRef/js/libs/screenfull.js
LinuxCApiRef/js/libs/screenfull.min.js
LinuxCApiRef/js/libs/zip.min.js
LinuxCApiRef/js/plugins/__init__.py
LinuxCApiRef/js/plugins/hypothesis.js
LinuxCApiRef/js/plugins/search.js
linux_c_api_ref-2024.3.1.0.dist-info/METADATA
linux_c_api_ref-2024.3.1.0.dist-info/WHEEL
linux_c_api_ref-2024.3.1.0.dist-info/entry_points.txt
linux_c_api_ref-2024.3.1.0.dist-info/top_level.txt
linux_c_api_ref-2024.3.1.0.dist-info/RECORD
